hello/__init__.py
hello/main.py
asher_hello_cli-0.1.1.dist-info/METADATA
asher_hello_cli-0.1.1.dist-info/WHEEL
asher_hello_cli-0.1.1.dist-info/entry_points.txt
asher_hello_cli-0.1.1.dist-info/RECORD
