Metadata-Version: 2.3
Name: asher-hello-cli
Version: 0.1.1
Summary: A simple CLI hello example using argparse.
License: MIT
Keywords: cli,hello,example
Author: Asher
Author-email: jasherleslie@gmail.com
Requires-Python: >=3.12
Classifier: License :: OSI Approved :: MIT License
Classifier: Programming Language :: Python :: 3
Classifier: Programming Language :: Python :: 3.12
Classifier: Programming Language :: Python :: 3.13
